LICENSE
README.md
setup.py
pyTONPublicAPI/__init__.py
pyTONPublicAPI/api.py
pyTONPublicAPI/servers.py
pyTONPublicAPI/tests.py
pyTONPublicAPI/version.py
pyTONPublicAPI.egg-info/PKG-INFO
pyTONPublicAPI.egg-info/SOURCES.txt
pyTONPublicAPI.egg-info/dependency_links.txt
pyTONPublicAPI.egg-info/top_level.txt