Metadata-Version: 2.1
Name: pyTONPublicAPI
Version: 0.0.5
Summary: Python TON.sh Public API
Home-page: https://github.com/Badiboy/pyTONPublicAPI
Author: Badiboy
License: MIT license
Keywords: TON Open Network API
Platform: UNKNOWN
Classifier: Development Status :: 3 - Alpha
Classifier: Programming Language :: Python :: 3
Classifier: License :: OSI Approved :: MIT License
Requires: requests
